fastapi_auth/__init__.py
fastapi_auth/auth.py
simple_fastapi_auth-1.1.dist-info/licenses/LICENSE
simple_fastapi_auth-1.1.dist-info/METADATA
simple_fastapi_auth-1.1.dist-info/WHEEL
simple_fastapi_auth-1.1.dist-info/top_level.txt
simple_fastapi_auth-1.1.dist-info/RECORD
