Metadata-Version: 2.4
Name: simple_fastapi_auth
Version: 1.1
Summary: A *heavily* opinionated library for simplifying the boilerplate of FastAPI authentication.
Author: Carlo Moro
Author-email: Carlo Moro <cnmoro@gmail.com>
Classifier: Programming Language :: Python :: 3
Classifier: License :: OSI Approved :: MIT License
Classifier: Operating System :: OS Independent
Requires-Python: >=3.7
License-File: LICENSE
Requires-Dist: python-jose
Requires-Dist: passlib
Requires-Dist: bcrypt
Requires-Dist: fastapi
Requires-Dist: python-multipart
Dynamic: author
Dynamic: license-file
Dynamic: requires-python
